{
  "name": "Urban Hearth",
  "footer_note": "Ask your server to see our dessert menu. Please inform your server if you have any dietary restrictions. We add a 20% gratuity for all parties of 6 or more.",
  "sections": [
    {
      "title": "Shared Plates",
      "items": [
        {
          "name": "Unicorn Oysters on the Half Shell",
          "price": "4 ea",
          "description": "cranberry ponzu · absinthe lime mignonette",
          "note": ""
        },
        {
          "name": "Hake Crudo in Hibiscus Leche de Tigre",
          "price": "26",
          "description": "crispy leek · pickled green strawberry · summer truffle",
          "note": ""
        },
        {
          "name": "Vadouvan Carrot Brochette",
          "price": "28",
          "description": "savory oat butter · cocoa emulsion · burnt satsuma",
          "note": ""
        },
        {
          "name": "Grilled Asparagus & Spring Forage Pistou",
          "price": "26",
          "description": "cultured sheep’s milk cheese · basil · hazelnut",
          "note": ""
        },
        {
          "name": "Blistered Kale with Whipped Tahini",
          "price": "28",
          "description": "fregula · szechuan sesame crisp · pickled apple · fermented chili",
          "note": ""
        },
        {
          "name": "Lovage Crème Brûlée with Sugar Snaps",
          "price": "30",
          "description": "clothbound cheddar · rye soil · pea tendrils",
          "note": ""
        },
        {
          "name": "Pan Seared Halibut",
          "price": "42",
          "description": "mussel conserva · dill beurre blanc · shaved fennel salad",
          "note": ""
        },
        {
          "name": "Chicken & Wild Mushrooms in Red Wine",
          "price": "44",
          "description": "serrano ham · pommes provençial · pearl onion agrodolce",
          "note": ""
        }
      ]
    },
    {
      "title": "Breads and Charcuterie",
      "items": [
        {
          "name": "Warm Mediterranean Olives",
          "price": "8",
          "description": "olive oil · preserved lemon · chili",
          "note": ""
        },
        {
          "name": "Big Buttermilk Biscuit",
          "price": "8",
          "description": "smoked maple miso butter",
          "note": ""
        },
        {
          "name": "Grilled Sourdough Focaccia",
          "price": "8",
          "description": "da lat spice · olive oil",
          "note": ""
        },
        {
          "name": "New England Nosh Board",
          "price": "29",
          "description": "choose 4 · served with crackers and confiture",
          "note": "Cheeses: Fiddlehead Tomme (NH), Camembert (NY), Great Hill Blue (MA), Jasper Hill Cheddar (VT), Vermont Chèvre (VT). Charcuterie: Rosette de Lyon (NY), Prosciutto de Parma (IT), N'duja (MA)."
        }
      ]
    }
  ]
}
